pwnc/__init__.py
pwnc/pwnc_exceptions.py
pwnc/pwnc_helpers.py
pwnc/pwnc_urllib3.py
pwnc/version.py
pwnc-0.0.1.dist-info/LICENSE
pwnc-0.0.1.dist-info/METADATA
pwnc-0.0.1.dist-info/WHEEL
pwnc-0.0.1.dist-info/top_level.txt
pwnc-0.0.1.dist-info/RECORD
