Metadata-Version: 2.1
Name: pwnc
Version: 0.0.1
Summary: A package for automating libc exploitation
Home-page: https://github.com/jhilbs3/pwnc
Author: Joe Hilbert
Author-email: jhilbs3@gmail.com
License: UNKNOWN
Platform: UNKNOWN
Classifier: Programming Language :: Python :: 3
Requires-Python: >=3.6
License-File: LICENSE
Requires-Dist: urllib3
